pyannotate_runtime/__init__.py
pyannotate_runtime/collect_types.py
pyannotate_tools/__init__.py
pyannotate_tools/annotations/__init__.py
pyannotate_tools/annotations/__main__.py
pyannotate_tools/annotations/infer.py
pyannotate_tools/annotations/main.py
pyannotate_tools/annotations/parse.py
pyannotate_tools/annotations/types.py
pyannotate_tools/fixes/__init__.py
pyannotate_tools/fixes/fix_annotate.py
pyannotate_tools/fixes/fix_annotate_json.py
pyannotate-1.0.7.dist-info/LICENSE
pyannotate-1.0.7.dist-info/METADATA
pyannotate-1.0.7.dist-info/WHEEL
pyannotate-1.0.7.dist-info/entry_points.txt
pyannotate-1.0.7.dist-info/top_level.txt
pyannotate-1.0.7.dist-info/RECORD
